truechecker/__init__.py
truechecker/api.py
truechecker/base.py
truechecker/const.py
truechecker/exceptions.py
truechecker/models/__init__.py
truechecker/models/job.py
truechecker/models/profile.py
truechecker/models/users.py
truechecker/utils/__init__.py
truechecker/utils/json.py
truechecker-2021.10.11.dist-info/LICENSE
truechecker-2021.10.11.dist-info/WHEEL
truechecker-2021.10.11.dist-info/METADATA
truechecker-2021.10.11.dist-info/RECORD
