Metadata-Version: 2.1
Name: truechecker
Version: 2021.10.11
Summary: Python client for True Checker API
Home-page: https://gitlab.com/true-web-app/true-checker/true-checker-python
License: MIT
Keywords: True Checker,Telegram,Bots
Author: Oleg A.
Author-email: oleg@trueweb.app
Maintainer: Oleg A.
Maintainer-email: oleg@trueweb.app
Requires-Python: >=3.7,<4.0
Classifier: License :: OSI Approved :: MIT License
Classifier: Programming Language :: Python :: 3
Classifier: Programming Language :: Python :: 3.10
Classifier: Programming Language :: Python :: 3.7
Classifier: Programming Language :: Python :: 3.8
Classifier: Programming Language :: Python :: 3.9
Requires-Dist: aiohttp (>=3.7,<4.0)
Requires-Dist: certifi (>=2021,<2022)
Requires-Dist: pydantic (>=1.8,<2.0)
Project-URL: Documentation, https://checker.trueweb.app/redoc/
Project-URL: Repository, https://gitlab.com/true-web-app/true-checker/true-checker-python
